[
  {
    "masaid": 1,
    "masadurumu": true,
    "tutar": 37,
    "siparis": [
      {
        "urunadi": "lahmacun",
        "adedi": 3,
        "not": ""
      },
      {
        "urunadi": "Dürüm",
        "adedi": 2,
        "not": "Zero"
      },
      {
        "urunadi": "Kola",
        "adedi": 4,
        "not": " 1 tanesi Zero"
      }
    ]
  },
  {
    "masaid": 2,
    "masadurumu": false,
    "tutar": 72,
    "siparis": [
      {
        "urunadi": "pide",
        "adedi": 3,
        "not": "2"
      },
      {
        "urunadi": "adana",
        "adedi": 2,
        "not": "Zero"
      },
      {
        "urunadi": "Kola",
        "adedi": 4,
        "not": " 1 tanesi Zero"
      }
    ]
  },
  {
    "masaid": 3,
    "masadurumu": false,
    "tutar": 142,
    "siparis": [
      {
        "urunadi": "çorba",
        "adedi": 3,
        "not": ""
      },
      {
        "urunadi": "iskender",
        "adedi": 2,
        "not": "Zero"
      },
      {
        "urunadi": "su",
        "adedi": 4,
        "not": " 1 tanesi Zero"
      }
    ]
  },
  {
    "masaid": 4,
    "masadurumu": true,
    "tutar": 122,
    "siparis": [
      {
        "urunadi": "lahmacun",
        "adedi": 3,
        "not": ""
      },
      {
        "urunadi": "Dürüm",
        "adedi": 2,
        "not": "Zero"
      },
      {
        "urunadi": "Kola",
        "adedi": 4,
        "not": " 1 tanesi Zero"
      }
    ]
  },
  {
    "masaid": 5,
    "masadurumu": true,
    "tutar": 422,
    "siparis": [
      {
        "urunadi": "fark",
        "adedi": 3,
        "not": "2"
      },
      {
        "urunadi": "var",
        "adedi": 2,
        "not": "Zero"
      },
      {
        "urunadi": "Kola",
        "adedi": 4,
        "not": " 1 tanesi Zero"
      }
    ]
  },
  {
    "masaid": 6,
    "masadurumu": true,
    "tutar": 82,
    "siparis": [
      {
        "urunadi": "lahmacun",
        "adedi": 3,
        "not": ""
      },
      {
        "urunadi": "Dürüm",
        "adedi": 2,
        "not": "Zero"
      },
      {
        "urunadi": "Kola",
        "adedi": 4,
        "not": " 1 tanesi Zero"
      }
    ]
  },
  {
    "masaid": 7,
    "masadurumu": false,
    "tutar": 71,
    "siparis": [
      {
        "urunadi": "2lahmacun",
        "adedi": 3,
        "not": "2"
      },
      {
        "urunadi": "2Dürüm",
        "adedi": 2,
        "not": "Zero"
      },
      {
        "urunadi": "Kola",
        "adedi": 4,
        "not": " 1 tanesi Zero"
      }
    ]
  },
  {
    "masaid": 8,
    "masadurumu": false,
    "tutar": 322,
    "siparis": [
      {
        "urunadi": "lahmacun",
        "adedi": 3,
        "not": ""
      },
      {
        "urunadi": "Dürüm",
        "adedi": 2,
        "not": "Zero"
      },
      {
        "urunadi": "Kola",
        "adedi": 4,
        "not": " 1 tanesi Zero"
      }
    ]
  },
  {
    "masaid": 9,
    "masadurumu": false,
    "tutar": 72,
    "siparis": [
      {
        "urunadi": "2lahmacun",
        "adedi": 3,
        "not": "2"
      },
      {
        "urunadi": "2Dürüm",
        "adedi": 2,
        "not": "Zero"
      },
      {
        "urunadi": "Kola",
        "adedi": 4,
        "not": " 1 tanesi Zero"
      }
    ]
  },
  {
    "masaid": 10,
    "masadurumu": true,
    "tutar": 32,
    "siparis": [
      {
        "urunadi": "lahmacun",
        "adedi": 3,
        "not": ""
      },
      {
        "urunadi": "Dürüm",
        "adedi": 2,
        "not": "Zero"
      },
      {
        "urunadi": "Kola",
        "adedi": 4,
        "not": " 1 tanesi Zero"
      }
    ]
  },
  {
    "masaid": 11,
    "masadurumu": false,
    "tutar": 72,
    "siparis": [
      {
        "urunadi": "2lahmacun",
        "adedi": 3,
        "not": "2"
      },
      {
        "urunadi": "2Dürüm",
        "adedi": 2,
        "not": "Zero"
      },
      {
        "urunadi": "Kola",
        "adedi": 4,
        "not": " 1 tanesi Zero"
      }
    ]
  },
  {
    "masaid": 12,
    "masadurumu": true,
    "tutar": 32,
    "siparis": [
      {
        "urunadi": "lahmacun",
        "adedi": 3,
        "not": ""
      },
      {
        "urunadi": "Dürüm",
        "adedi": 2,
        "not": "Zero"
      },
      {
        "urunadi": "Kola",
        "adedi": 4,
        "not": " 1 tanesi Zero"
      }
    ]
  },
  {
    "masaid": 13,
    "masadurumu": false,
    "tutar": 72,
    "siparis": [
      {
        "urunadi": "2lahmacun",
        "adedi": 3,
        "not": "2"
      },
      {
        "urunadi": "2Dürüm",
        "adedi": 2,
        "not": "Zero"
      },
      {
        "urunadi": "Kola",
        "adedi": 4,
        "not": " 1 tanesi Zero"
      }
    ]
  }
]